ngclearn/__init__.py
ngclearn/components/__init__.py
ngclearn/components/jaxComponent.py
ngclearn/components/input_encoders/__init__.py
ngclearn/components/input_encoders/bernoulliCell.py
ngclearn/components/input_encoders/latencyCell.py
ngclearn/components/input_encoders/phasorCell.py
ngclearn/components/input_encoders/poissonCell.py
ngclearn/components/neurons/__init__.py
ngclearn/components/neurons/graded/__init__.py
ngclearn/components/neurons/graded/bernoulliErrorCell.py
ngclearn/components/neurons/graded/gaussianErrorCell.py
ngclearn/components/neurons/graded/laplacianErrorCell.py
ngclearn/components/neurons/graded/leakyNoiseCell.py
ngclearn/components/neurons/graded/rateCell.py
ngclearn/components/neurons/graded/rewardErrorCell.py
ngclearn/components/neurons/spiking/IFCell.py
ngclearn/components/neurons/spiking/LIFCell.py
ngclearn/components/neurons/spiking/RAFCell.py
ngclearn/components/neurons/spiking/WTASCell.py
ngclearn/components/neurons/spiking/__init__.py
ngclearn/components/neurons/spiking/adExCell.py
ngclearn/components/neurons/spiking/fitzhughNagumoCell.py
ngclearn/components/neurons/spiking/hodgkinHuxleyCell.py
ngclearn/components/neurons/spiking/izhikevichCell.py
ngclearn/components/neurons/spiking/quadLIFCell.py
ngclearn/components/neurons/spiking/sLIFCell.py
ngclearn/components/other/__init__.py
ngclearn/components/other/expKernel.py
ngclearn/components/other/varTrace.py
ngclearn/components/synapses/STPDenseSynapse.py
ngclearn/components/synapses/__init__.py
ngclearn/components/synapses/alphaSynapse.py
ngclearn/components/synapses/denseSynapse.py
ngclearn/components/synapses/doubleExpSynapse.py
ngclearn/components/synapses/exponentialSynapse.py
ngclearn/components/synapses/staticSynapse.py
ngclearn/components/synapses/convolution/__init__.py
ngclearn/components/synapses/convolution/convSynapse.py
ngclearn/components/synapses/convolution/deconvSynapse.py
ngclearn/components/synapses/convolution/hebbianConvSynapse.py
ngclearn-3.0.1.dist-info/licenses/AUTHORS
ngclearn-3.0.1.dist-info/licenses/LICENSE
ngclearn-3.0.1.dist-info/METADATA
ngclearn-3.0.1.dist-info/WHEEL
ngclearn-3.0.1.dist-info/top_level.txt
ngclearn-3.0.1.dist-info/RECORD
