Metadata-Version: 2.4
Name: ngclearn
Version: 3.0.1
Summary: Simulation software for building and analyzing computational neuroscience models, brain-inspired computing systems, and NeuroAI agents.
Author-email: Alexander Ororbia <ago@cs.rit.edu>, William Gebhardt <wdg1351@rit.edu>
License-Expression: BSD-3-Clause
Project-URL: Homepage, https://github.com/NACLab/ngc-learn
Project-URL: Documentation, https://ngc-learn.readthedocs.io/
Project-URL: Lab Page, https://www.cs.rit.edu/~ago/nac_lab.html
Project-URL: Changelog, https://github.com/NACLab/ngc-learn/blob/main/history.txt
Keywords: python,ngc-learn,predictive-processing,predictive-coding,neuro-ai,jax,spiking-neural-networks,biomimetics,bionics,computational-neuroscience
Classifier: Development Status :: 4 - Beta
Classifier: Intended Audience :: Education
Classifier: Intended Audience :: Science/Research
Classifier: Intended Audience :: Developers
Classifier: Topic :: Scientific/Engineering
Classifier: Topic :: Scientific/Engineering :: Mathematics
Classifier: Topic :: Scientific/Engineering :: Artificial Intelligence
Classifier: Programming Language :: Python
Classifier: Programming Language :: Python :: 3
Classifier: Programming Language :: Python :: 3.10
Classifier: Programming Language :: Python :: 3.11
Classifier: Operating System :: Unix
Requires-Python: >=3.10
License-File: LICENSE
License-File: AUTHORS
Requires-Dist: numpy>=1.26.4
Requires-Dist: scikit-learn>=1.6.1
Requires-Dist: scipy>=1.15.2
Requires-Dist: matplotlib>=3.10.1
Requires-Dist: jax>=0.4.28
Requires-Dist: jaxlib>=0.4.28
Requires-Dist: ngcsimlib>=3.0.0
Requires-Dist: imageio>=2.37.0
Requires-Dist: pandas>=2.2.3
Dynamic: license-file
